flickr_api/__init__.py
flickr_api/downloader.py
flickr_api/exceptions.py
flickr_api/fixtures.py
flickr_api/parsers.py
flickr_api/py.typed
flickr_api/retrying.py
flickr_api/api/__init__.py
flickr_api/api/base.py
flickr_api/api/comment_methods.py
flickr_api/api/commons_methods.py
flickr_api/api/license_methods.py
flickr_api/api/single_photo_methods.py
flickr_api/api/user_methods.py
flickr_api/models/__init__.py
flickr_api/models/contexts.py
flickr_api/models/licenses.py
flickr_api/models/machine_tags.py
flickr_api/models/photo.py
flickr_api/models/sizes.py
flickr_api/models/users.py
flickr_photos_api-3.12.1.dist-info/licenses/LICENSE-APACHE
flickr_photos_api-3.12.1.dist-info/licenses/LICENSE-MIT
flickr_photos_api-3.12.1.dist-info/METADATA
flickr_photos_api-3.12.1.dist-info/WHEEL
flickr_photos_api-3.12.1.dist-info/top_level.txt
flickr_photos_api-3.12.1.dist-info/RECORD
