Metadata-Version: 2.4
Name: flickr-photos-api
Version: 3.12.1
Summary: Look up information about photos and collections of photos from Flickr
Author-email: Flickr Foundation <hello@flickr.org>
Maintainer-email: Alex Chan <alex@flickr.org>
License-Expression: MIT AND (Apache-2.0)
Project-URL: Homepage, https://github.com/Flickr-Foundation/flickr-photos-api
Project-URL: Changelog, https://github.com/Flickr-Foundation/flickr-photos-api/blob/main/CHANGELOG.md
Keywords: flickr
Classifier: Development Status :: 5 - Production/Stable
Classifier: Programming Language :: Python :: 3.12
Requires-Python: >=3.12
License-File: LICENSE-APACHE
License-File: LICENSE-MIT
Requires-Dist: flickr_url_parser>=1.10.0
Requires-Dist: httpx
Requires-Dist: silver-nitrate[xml]>=1.5.0
Requires-Dist: tenacity
Provides-Extra: fixtures
Requires-Dist: silver-nitrate[cassettes]; extra == "fixtures"
Provides-Extra: oauth
Requires-Dist: authlib; extra == "oauth"
Dynamic: license-file
